<configuration debug="true">
    <property name="logHome" value="./data/logs" />

    <appender name="STDOUT" class="ch.qos.logback.core.ConsoleAppender">
        <encoder class="ch.qos.logback.classic.encoder.PatternLayoutEncoder">
            <pattern>%d{yyyy-MM-dd HH:mm:ss.SSS} [%thread] %-5level %logger{50} - %msg%n</pattern>
        </encoder>
    </appender>

    <appender name="fileAppender" class="ch.qos.logback.core.rolling.RollingFileAppender">
        <filter class="ch.qos.logback.classic.filter.ThresholdFilter">
            <level>DEBUG</level>
        </filter>
        <rollingPolicy class="ch.qos.logback.core.rolling.TimeBasedRollingPolicy">
            <fileNamePattern>${logHome}/%d{yyyyMMdd}/subway.%d{yyyyMMdd}.%i.log</fileNamePattern>
            <timeBasedFileNamingAndTriggeringPolicy class="ch.qos.logback.core.rolling.SizeAndTimeBasedFNATP">
                <maxFileSize>15MB</maxFileSize>
            </timeBasedFileNamingAndTriggeringPolicy>
        </rollingPolicy>
        <encoder>
            <Pattern>
                %d{yyyy-MM-dd HH:mm:ss.SSS} %thread %-5level %logger - %m%n
            </Pattern>
        </encoder>
    </appender>

    <root level="info">
        <appender-ref ref="STDOUT" />
        <appender-ref ref="fileAppender" />
    </root>

</configuration>